rpds/__init__.py
rpds/header.py
rpds/item.py
rpds/load_file.py
rpds-1.7.1.dist-info/DESCRIPTION.rst
rpds-1.7.1.dist-info/METADATA
rpds-1.7.1.dist-info/RECORD
rpds-1.7.1.dist-info/WHEEL
rpds-1.7.1.dist-info/metadata.json
rpds-1.7.1.dist-info/top_level.txt
