Metadata-Version: 2.0
Name: rpds
Version: 1.7.1
Summary: A multi-use Python-based data storage format.
Home-page: https://github.com/DeflatedPickle/rpds
Author: DeflatedPickle/Dibbo, Pytato
Author-email: DeflatedPickle@gmail.com
License: MIT
Keywords: rpds,rpd,data,storage
Platform: UNKNOWN
Classifier: Intended Audience :: Developers
Classifier: License :: OSI Approved :: MIT License
Classifier: Programming Language :: Python :: 3.4
Classifier: Programming Language :: Python :: 3.5
